{
  "type": "object",
  "properties": {
    "provider_id": {
      "type": "string"
    },
    "provider_name": {
      "type": "string"
    },
    "village": {
      "type": "string"
    },
    "address": {
      "type": "string"
    },
    "headline": {
      "type": "string"
    },
    "body": {
      "type": "string"
    },
    "image_url": {
      "type": "string"
    },
    "deal_expires_at": {
      "type": "string"
    },
    "is_active": {
      "type": "boolean"
    },
    "next_headline": {
      "type": "string"
    },
    "next_body": {
      "type": "string"
    },
    "next_address": {
      "type": "string"
    },
    "next_village": {
      "type": "string"
    },
    "next_image_url": {
      "type": "string"
    },
    "next_deal_expires_at": {
      "type": "string"
    }
  },
  "required": [],
  "name": "ClassifiedAd"
}